{
  "radars": [
    {
      "id": "092dddda-bcd4-4d25-a3ac-e7af2c9d4de8",
      "latitude": -34.852269,
      "longitude": 138.574143,
      "street": "Gallipoli Dr",
      "city": "Regency Park",
      "type": "mobile",
      "timestamp": "2025-12-17T05:23:26Z",
      "reported_at": "2025-12-17T04:43:30Z"
    },
    {
      "id": "4a15a468-3c04-4134-b3be-c3af33484db0",
      "latitude": -35.018858,
      "longitude": 138.623494,
      "street": "Watahuna Av",
      "city": "Hawthorndene",
      "type": "mobile",
      "timestamp": "2025-12-17T05:23:26Z",
      "reported_at": "2025-12-17T04:29:25Z"
    },
    {
      "id": "9d858e11-045c-4e7f-9d7e-4383abd22cc1",
      "latitude": -34.859022,
      "longitude": 138.521758,
      "street": "Torrens Rd",
      "city": "Rosewater",
      "type": "mobile",
      "timestamp": "2025-12-17T05:23:26Z",
      "reported_at": "2025-12-17T05:06:51Z"
    },
    {
      "id": "031ce587-d2e8-4c6c-9c79-ce32cb1dcd53",
      "latitude": -35.009458,
      "longitude": 138.763143,
      "street": "Mount Barker Rd",
      "city": "Bridgewater",
      "type": "mobile",
      "timestamp": "2025-12-17T05:23:26Z",
      "reported_at": "2025-12-17T02:27:13Z"
    },
    {
      "id": "3763dcfa-5332-4578-8b9c-f392f0f37b04",
      "latitude": -34.916156,
      "longitude": 138.588294,
      "street": "War Memorial Dr",
      "city": "North Adelaide",
      "type": "mobile",
      "timestamp": "2025-12-17T05:23:26Z",
      "reported_at": "2025-12-17T04:20:37Z"
    },
    {
      "id": "fbdd2055-9a92-493b-8856-e847c0b59de5",
      "latitude": -34.707319,
      "longitude": 138.651783,
      "street": "Bellchambers Rd",
      "city": "Edinburgh North",
      "type": "mobile",
      "timestamp": "2025-12-17T05:23:26Z",
      "reported_at": "2025-12-17T05:09:42Z"
    },
    {
      "id": "7febec80-26ac-46d1-bbc9-7c4edd0a0a33",
      "latitude": -34.742973,
      "longitude": 138.668605,
      "street": "Haydown Rd",
      "city": "Elizabeth Vale",
      "type": "mobile",
      "timestamp": "2025-12-17T05:23:26Z",
      "reported_at": "2025-12-17T05:22:10Z"
    },
    {
      "id": "9d7dd033-d319-4eaa-8058-be8d61181887",
      "latitude": -34.700147,
      "longitude": 138.66539,
      "street": "Peachey Rd",
      "city": "Davoren Park",
      "type": "mobile",
      "timestamp": "2025-12-17T05:23:26Z",
      "reported_at": "2025-12-17T05:08:10Z"
    },
    {
      "id": "c9d46a91-f7fc-4f08-b635-298b44ee18a8",
      "latitude": -34.749217,
      "longitude": 138.681985,
      "street": "Black Top Rd",
      "city": "Hillbank",
      "type": "mobile",
      "timestamp": "2025-12-17T05:23:26Z",
      "reported_at": "2025-12-17T05:13:12Z"
    },
    {
      "id": "a8940bba-69fe-432d-a8bd-109365674dfe",
      "latitude": -34.89897,
      "longitude": 138.593103,
      "street": "R1 - Fitzroy Tce (City Ring Route)",
      "city": "Thorngate",
      "type": "mobile",
      "timestamp": "2025-12-17T05:23:26Z",
      "reported_at": "2025-12-17T05:20:25Z"
    },
    {
      "id": "9455cbac-a28e-4804-bffe-33a8002d5413",
      "latitude": -34.959632,
      "longitude": 138.730987,
      "street": "B26 - Greenhill Rd",
      "city": "Summertown",
      "type": "mobile",
      "timestamp": "2025-12-17T05:23:26Z",
      "reported_at": "2025-12-17T02:05:56Z"
    },
    {
      "id": "c239910b-3d68-4d48-bace-6fae55c2d946",
      "latitude": -34.749145,
      "longitude": 138.665769,
      "street": "A9 - John Rice Av",
      "city": "Elizabeth Vale",
      "type": "mobile",
      "timestamp": "2025-12-17T05:23:26Z",
      "reported_at": "2025-12-17T05:02:09Z"
    },
    {
      "id": "6add68f2-64f5-4cd2-b7fe-6cc91afe9b47",
      "latitude": -34.795559,
      "longitude": 138.707567,
      "street": "A11 - The Grove Way",
      "city": "Golden Grove",
      "type": "mobile",
      "timestamp": "2025-12-17T05:23:26Z",
      "reported_at": "2025-12-17T04:56:33Z"
    },
    {
      "id": "c2532c94-6ca8-46c3-ac25-499005e0e3e4",
      "latitude": -34.67901,
      "longitude": 138.696404,
      "street": "A20 - Main North Rd",
      "city": "Evanston South",
      "type": "mobile",
      "timestamp": "2025-12-17T05:23:26Z",
      "reported_at": "2025-12-17T05:10:54Z"
    }
  ]
}
