{
  "radars": [
    {
      "id": "272a05cd-1f17-4603-96f6-0a03c8e27508",
      "latitude": -34.821124,
      "longitude": 138.611396,
      "street": "Mawson Lakes Bvd",
      "city": "Mawson Lakes",
      "type": "mobile",
      "timestamp": "2025-12-03T04:01:45Z",
      "reported_at": "2025-12-03T00:59:57Z"
    },
    {
      "id": "56354480-47f0-4908-926a-258497da3b31",
      "latitude": -34.902602,
      "longitude": 138.575003,
      "street": "Chief St",
      "city": "Brompton",
      "type": "mobile",
      "timestamp": "2025-12-03T04:01:45Z",
      "reported_at": "2025-12-03T03:27:42Z"
    },
    {
      "id": "866b3fae-801b-44a9-af41-19339edc4b76",
      "latitude": -34.760094,
      "longitude": 138.677555,
      "street": "Target Hill Rd",
      "city": "Salisbury Heights",
      "type": "mobile",
      "timestamp": "2025-12-03T04:01:45Z",
      "reported_at": "2025-12-03T02:29:33Z"
    },
    {
      "id": "fcdea16e-5548-4116-a1b1-b232c789accc",
      "latitude": -34.747243,
      "longitude": 138.607386,
      "street": "Bolivar Rd",
      "city": "Paralowie",
      "type": "mobile",
      "timestamp": "2025-12-03T04:01:45Z",
      "reported_at": "2025-12-03T00:44:59Z"
    },
    {
      "id": "d98fb64b-ea8d-45c9-8a37-3c1a85ebcb20",
      "latitude": -34.975926,
      "longitude": 138.526046,
      "street": "A5 - Anzac Hwy",
      "city": "Glenelg North",
      "type": "mobile",
      "timestamp": "2025-12-03T04:01:45Z",
      "reported_at": "2025-12-03T02:48:50Z"
    },
    {
      "id": "723a8b3e-de07-4cfe-bd1a-504f59dcc2cd",
      "latitude": -34.794199,
      "longitude": 138.61288,
      "street": "A9 - Salisbury Hwy",
      "city": "Parafield Gardens",
      "type": "mobile",
      "timestamp": "2025-12-03T04:01:45Z",
      "reported_at": "2025-12-03T01:17:19Z"
    },
    {
      "id": "2c9a5cb2-1c83-4422-9955-f5ca4c114c90",
      "latitude": -35.090595,
      "longitude": 138.527517,
      "street": "M2 - Southern Exp",
      "city": "Reynella",
      "type": "mobile",
      "timestamp": "2025-12-03T04:01:45Z",
      "reported_at": "2025-12-03T03:35:49Z"
    }
  ]
}
