{
  "radars": [
    {
      "id": "add91899-968d-4eaf-b652-3cf9a6b8037c",
      "latitude": -34.99315,
      "longitude": 138.513426,
      "street": "Tarlton St",
      "city": "Somerton Park",
      "type": "mobile",
      "timestamp": "2025-12-14T08:26:42Z",
      "reported_at": "2025-12-14T04:52:54Z"
    },
    {
      "id": "9376d7ad-b2c4-4c81-9a25-c9222bd0e729",
      "latitude": -35.102014,
      "longitude": 138.499502,
      "street": "Meyer Rd",
      "city": "Lonsdale",
      "type": "mobile",
      "timestamp": "2025-12-14T08:26:42Z",
      "reported_at": "2025-12-14T04:50:02Z"
    },
    {
      "id": "833f6170-ee5e-4f8c-8edb-b2cf0041a619",
      "latitude": -35.111459,
      "longitude": 138.507353,
      "street": "Aldershot Rd",
      "city": "Lonsdale",
      "type": "mobile",
      "timestamp": "2025-12-14T08:26:42Z",
      "reported_at": "2025-12-14T05:21:59Z"
    },
    {
      "id": "c75ec7fb-01f1-4f18-9f8b-6ee670f03602",
      "latitude": -35.131095,
      "longitude": 138.472925,
      "street": "Gulfview Rd",
      "city": "Christies Beach",
      "type": "mobile",
      "timestamp": "2025-12-14T08:26:42Z",
      "reported_at": "2025-12-14T05:16:00Z"
    },
    {
      "id": "7a3b199b-29ab-40eb-b332-9bee73915611",
      "latitude": -35.094495,
      "longitude": 138.528836,
      "street": "Grant Rd",
      "city": "Reynella",
      "type": "mobile",
      "timestamp": "2025-12-14T08:26:42Z",
      "reported_at": "2025-12-14T05:08:36Z"
    },
    {
      "id": "b7e03819-5524-4ae8-92bd-e5bfd27e5a27",
      "latitude": -35.06583,
      "longitude": 138.542551,
      "street": "Adams Rd",
      "city": "Trott Park",
      "type": "mobile",
      "timestamp": "2025-12-14T08:26:42Z",
      "reported_at": "2025-12-14T05:26:45Z"
    },
    {
      "id": "1c7785b1-8d91-4839-9401-341a6fc5f35c",
      "latitude": -35.087476,
      "longitude": 138.543278,
      "street": "Old South Rd",
      "city": "Old Reynella",
      "type": "mobile",
      "timestamp": "2025-12-14T08:26:42Z",
      "reported_at": "2025-12-14T05:20:58Z"
    },
    {
      "id": "a788ef0c-7288-42a8-a1ba-1faa56b11f1e",
      "latitude": -35.134637,
      "longitude": 138.485875,
      "street": "A15 - Dyson Rd",
      "city": "Christies Beach",
      "type": "mobile",
      "timestamp": "2025-12-14T08:26:42Z",
      "reported_at": "2025-12-14T08:00:10Z"
    },
    {
      "id": "9b18b376-7edc-4c72-9fad-7510d6e06d54",
      "latitude": -34.89109,
      "longitude": 138.513706,
      "street": "A15 - Tapleys Hill Rd",
      "city": "Seaton",
      "type": "mobile",
      "timestamp": "2025-12-14T08:26:42Z",
      "reported_at": "2025-12-14T08:08:10Z"
    }
  ]
}
