{
  "radars": [
    {
      "id": "7644a493-f7bb-4c4b-bcf2-2b692a19698b",
      "latitude": -34.84984,
      "longitude": 138.668639,
      "street": "A10 - North East Rd",
      "city": "Holden Hill",
      "type": "mobile",
      "timestamp": "2025-11-22T15:17:56Z",
      "reported_at": "2025-11-22T14:43:39Z"
    },
    {
      "id": "c3cd11f1-a55f-4e74-913d-918bbcc94fe5",
      "latitude": -34.904943,
      "longitude": 138.571092,
      "street": "A7 - Port Rd",
      "city": "Hindmarsh",
      "type": "mobile",
      "timestamp": "2025-11-22T15:17:56Z",
      "reported_at": "2025-11-22T14:17:20Z"
    },
    {
      "id": "47d7f88b-1082-422c-a438-7bded37aa4b9",
      "latitude": -34.96246,
      "longitude": 138.557019,
      "street": "A5 - Anzac Hwy",
      "city": "Plympton",
      "type": "mobile",
      "timestamp": "2025-11-22T15:17:56Z",
      "reported_at": "2025-11-22T14:52:59Z"
    },
    {
      "id": "26e48083-f770-460d-ba9a-135ce428bb29",
      "latitude": -34.883781,
      "longitude": 138.57156,
      "street": "M2 - North-South Mwy",
      "city": "Croydon Park",
      "type": "mobile",
      "timestamp": "2025-11-22T15:17:56Z",
      "reported_at": "2025-11-22T14:17:14Z"
    },
    {
      "id": "c47bcd6d-b403-4932-8054-75e51ce0e67e",
      "latitude": -35.04841,
      "longitude": 138.548493,
      "street": "M2 - Southern Exp",
      "city": "Darlington",
      "type": "mobile",
      "timestamp": "2025-11-22T15:17:56Z",
      "reported_at": "2025-11-22T14:57:50Z"
    }
  ]
}
