{
  "radars": [
    {
      "id": "644c1e77-3fb0-46ea-8bb1-9f3cacae8f16",
      "latitude": -34.968334,
      "longitude": 138.543905,
      "street": "Stonehouse Av",
      "city": "Camden Park",
      "type": "mobile",
      "timestamp": "2025-11-25T21:18:44Z",
      "reported_at": "2025-11-25T20:43:37Z"
    },
    {
      "id": "28789b1e-349d-4bdd-a1bb-27d914881697",
      "latitude": -34.956306,
      "longitude": 138.614713,
      "street": "Duthy St",
      "city": "Malvern",
      "type": "mobile",
      "timestamp": "2025-11-25T21:18:44Z",
      "reported_at": "2025-11-25T20:58:54Z"
    },
    {
      "id": "95823f0b-d153-421b-af6d-9853e829d8e8",
      "latitude": -34.958291,
      "longitude": 138.530915,
      "street": "James Melrose Av",
      "city": "Adelaide Airport",
      "type": "mobile",
      "timestamp": "2025-11-25T21:18:44Z",
      "reported_at": "2025-11-25T20:17:15Z"
    },
    {
      "id": "9848dd7e-c30f-4c86-8ec5-abd68a1d9a9d",
      "latitude": -35.105979,
      "longitude": 138.510653,
      "street": "Sherriffs Rd",
      "city": "Reynella",
      "type": "mobile",
      "timestamp": "2025-11-25T21:18:44Z",
      "reported_at": "2025-11-25T21:10:45Z"
    },
    {
      "id": "7019a5bf-e290-44ca-95ca-1fad573491ab",
      "latitude": -34.875315,
      "longitude": 138.484149,
      "street": "Military Rd",
      "city": "West Lakes Shore",
      "type": "mobile",
      "timestamp": "2025-11-25T21:18:44Z",
      "reported_at": "2025-11-25T21:01:54Z"
    },
    {
      "id": "64075f5a-fa60-4239-ac16-7aec9d24b1c6",
      "latitude": -35.10605,
      "longitude": 138.506234,
      "street": "Sherriffs Rd",
      "city": "Lonsdale",
      "type": "mobile",
      "timestamp": "2025-11-25T21:18:44Z",
      "reported_at": "2025-11-25T21:04:43Z"
    },
    {
      "id": "dc446a10-e2da-4e9f-962f-bd678c9950b2",
      "latitude": -34.992512,
      "longitude": 138.580488,
      "street": "Daws Rd",
      "city": "Melrose Park",
      "type": "mobile",
      "timestamp": "2025-11-25T21:18:44Z",
      "reported_at": "2025-11-25T21:16:27Z"
    },
    {
      "id": "e1011f76-3e47-4ca6-9449-c451a728ca56",
      "latitude": -35.083793,
      "longitude": 138.583165,
      "street": "Chandlers Hill Rd",
      "city": "Happy Valley",
      "type": "mobile",
      "timestamp": "2025-11-25T21:18:44Z",
      "reported_at": "2025-11-25T20:59:13Z"
    },
    {
      "id": "a20d4a9b-0940-4e24-85dd-dc94295ddff2",
      "latitude": -34.922726,
      "longitude": 138.593472,
      "street": "Morphett St",
      "city": "Adelaide",
      "type": "mobile",
      "timestamp": "2025-11-25T21:18:44Z",
      "reported_at": "2025-11-25T21:04:31Z"
    },
    {
      "id": "76de8996-3fd7-4e19-a50d-f5efc652b61b",
      "latitude": -34.902376,
      "longitude": 138.620696,
      "street": "Stephen Tce",
      "city": "St. Peters",
      "type": "mobile",
      "timestamp": "2025-11-25T21:18:44Z",
      "reported_at": "2025-11-25T21:03:10Z"
    },
    {
      "id": "068717f3-8017-4bf0-8f4b-6b4c29a663cf",
      "latitude": -34.899054,
      "longitude": 138.616567,
      "street": "Stephen Tce",
      "city": "Walkerville",
      "type": "mobile",
      "timestamp": "2025-11-25T21:18:44Z",
      "reported_at": "2025-11-25T21:02:13Z"
    },
    {
      "id": "a063a147-320d-446b-8018-19f0d6809257",
      "latitude": -34.919228,
      "longitude": 138.622998,
      "street": "Fullarton Rd",
      "city": "Kent Town",
      "type": "mobile",
      "timestamp": "2025-11-25T21:18:44Z",
      "reported_at": "2025-11-25T21:09:45Z"
    }
  ]
}
