{
  "radars": [
    {
      "id": "64a76dec-e40a-4c1f-8fe5-28a84302d554",
      "latitude": -35.071275,
      "longitude": 138.530887,
      "street": "Adams Rd",
      "city": "Sheidow Park",
      "type": "mobile",
      "timestamp": "2026-01-11T04:00:19Z",
      "reported_at": "2026-01-11T02:53:29Z"
    },
    {
      "id": "5f23b8f5-727d-44ce-a163-c8a781c1ad73",
      "latitude": -35.122554,
      "longitude": 138.536123,
      "street": "States Rd",
      "city": "Morphett Vale",
      "type": "mobile",
      "timestamp": "2026-01-11T04:00:19Z",
      "reported_at": "2026-01-10T23:48:37Z"
    },
    {
      "id": "44854d40-e572-40f9-acb8-0d886e871349",
      "latitude": -35.135686,
      "longitude": 138.485954,
      "street": "A15 - Dyson Rd",
      "city": "Christies Beach",
      "type": "mobile",
      "timestamp": "2026-01-11T04:00:19Z",
      "reported_at": "2026-01-10T23:44:53Z"
    },
    {
      "id": "60fcc4f3-0cc7-4eb3-96fd-643d7903379d",
      "latitude": -34.85164,
      "longitude": 138.666916,
      "street": "A10 - North East Rd",
      "city": "Holden Hill",
      "type": "mobile",
      "timestamp": "2026-01-11T04:00:19Z",
      "reported_at": "2026-01-11T03:33:38Z"
    }
  ]
}
