{
  "radars": [
    {
      "id": "5fc7ae7c-f457-4689-ba4f-de74fbf53076",
      "latitude": -34.79593,
      "longitude": 138.641105,
      "street": "Nobby Buckley Dr",
      "city": "Parafield",
      "type": "mobile",
      "timestamp": "2025-12-01T07:43:11Z",
      "reported_at": "2025-12-01T05:19:59Z"
    },
    {
      "id": "ae3ad539-9cdf-4c0a-939a-2b5f6edc3520",
      "latitude": -34.759924,
      "longitude": 138.664113,
      "street": "Goddard Dr",
      "city": "Salisbury Park",
      "type": "mobile",
      "timestamp": "2025-12-01T07:43:11Z",
      "reported_at": "2025-12-01T06:53:48Z"
    },
    {
      "id": "eefdae84-7050-4202-ae1d-5d01b988963b",
      "latitude": -34.700143,
      "longitude": 138.720564,
      "street": "Uley Rd",
      "city": "Craigmore",
      "type": "mobile",
      "timestamp": "2025-12-01T07:43:11Z",
      "reported_at": "2025-12-01T05:31:12Z"
    },
    {
      "id": "83bac9b2-0f88-47cb-87dc-de475a03ffd4",
      "latitude": -34.696025,
      "longitude": 138.666399,
      "street": "Fordingbridge Rd",
      "city": "Davoren Park",
      "type": "mobile",
      "timestamp": "2025-12-01T07:43:11Z",
      "reported_at": "2025-12-01T05:14:59Z"
    },
    {
      "id": "5e668dc6-da17-4788-9c2b-c23f791911b7",
      "latitude": -34.721907,
      "longitude": 138.642892,
      "street": "West Av",
      "city": "Edinburgh",
      "type": "mobile",
      "timestamp": "2025-12-01T07:43:11Z",
      "reported_at": "2025-12-01T05:18:36Z"
    },
    {
      "id": "ff6d7f6f-46cd-4163-927c-1d8e926b37c7",
      "latitude": -34.872972,
      "longitude": 138.616076,
      "street": "Regency Rd",
      "city": "Broadview",
      "type": "mobile",
      "timestamp": "2025-12-01T07:43:11Z",
      "reported_at": "2025-12-01T07:31:40Z"
    },
    {
      "id": "88d7ffb0-f75f-4fb5-9eb8-6fbeef92e971",
      "latitude": -34.740475,
      "longitude": 138.711383,
      "street": "Black Top Rd",
      "city": "Gould Creek",
      "type": "mobile",
      "timestamp": "2025-12-01T07:43:11Z",
      "reported_at": "2025-12-01T05:48:48Z"
    },
    {
      "id": "401e1e3d-25d3-4f50-bf11-372ec178c26a",
      "latitude": -35.063122,
      "longitude": 138.534303,
      "street": "A15 - Lonsdale Rd",
      "city": "Hallett Cove",
      "type": "mobile",
      "timestamp": "2025-12-01T07:43:11Z",
      "reported_at": "2025-12-01T07:21:25Z"
    },
    {
      "id": "47377d5b-e6da-4173-9b9a-d68dc6ffd799",
      "latitude": -34.827803,
      "longitude": 138.694567,
      "street": "A10 - North East Rd",
      "city": "St. Agnes",
      "type": "mobile",
      "timestamp": "2025-12-01T07:43:11Z",
      "reported_at": "2025-12-01T07:25:25Z"
    },
    {
      "id": "dde37d15-3f59-40d9-b540-f0e83d3002c9",
      "latitude": -34.711949,
      "longitude": 138.570991,
      "street": "M2 - North-South Mwy",
      "city": "Waterloo Corner",
      "type": "mobile",
      "timestamp": "2025-12-01T07:43:11Z",
      "reported_at": "2025-12-01T07:30:24Z"
    }
  ]
}
