{
  "radars": [
    {
      "id": "f29ea57d-4213-4eae-af38-f8b054b4ad38",
      "latitude": -34.914388,
      "longitude": 138.585455,
      "street": "War Memorial Dr",
      "city": "North Adelaide",
      "type": "mobile",
      "timestamp": "2026-01-25T00:00:15Z",
      "reported_at": "2026-01-24T20:55:17Z"
    },
    {
      "id": "36006cf2-f2de-428b-8948-8626ecfba5ab",
      "latitude": -34.903627,
      "longitude": 138.599761,
      "street": "LeFevre Tce",
      "city": "North Adelaide",
      "type": "mobile",
      "timestamp": "2026-01-25T00:00:15Z",
      "reported_at": "2026-01-24T22:21:49Z"
    },
    {
      "id": "d90151bf-91f3-4ef7-a733-c9fff5a98a96",
      "latitude": -34.925057,
      "longitude": 138.614446,
      "street": "Bartels Rd",
      "city": "Adelaide",
      "type": "mobile",
      "timestamp": "2026-01-25T00:00:15Z",
      "reported_at": "2026-01-24T23:00:16Z"
    },
    {
      "id": "ccf13fbb-9dcd-46cf-baa2-4011d2d754d2",
      "latitude": -34.805949,
      "longitude": 138.618477,
      "street": "Elder Smith Rd",
      "city": "Mawson Lakes",
      "type": "mobile",
      "timestamp": "2026-01-25T00:00:15Z",
      "reported_at": "2026-01-24T23:33:33Z"
    },
    {
      "id": "87f4cbc0-da29-4193-9e21-d15805cf5b1d",
      "latitude": -34.937657,
      "longitude": 138.586926,
      "street": "A5 - Anzac Hwy",
      "city": "Adelaide",
      "type": "mobile",
      "timestamp": "2026-01-25T00:00:15Z",
      "reported_at": "2026-01-24T22:11:38Z"
    },
    {
      "id": "d3509160-83fc-40be-90d2-e7485febcf3d",
      "latitude": -34.940799,
      "longitude": 138.611,
      "street": "R1 - Greenhill Rd (City Ring Route)",
      "city": "Parkside",
      "type": "mobile",
      "timestamp": "2026-01-25T00:00:15Z",
      "reported_at": "2026-01-24T21:05:24Z"
    },
    {
      "id": "8c47585d-e712-4326-be84-95b77ba9732a",
      "latitude": -34.96418,
      "longitude": 138.633279,
      "street": "A3 - Cross Rd",
      "city": "Myrtle Bank",
      "type": "mobile",
      "timestamp": "2026-01-25T00:00:15Z",
      "reported_at": "2026-01-24T20:55:40Z"
    },
    {
      "id": "e4029826-116a-4b2f-8095-5a8d49bb3880",
      "latitude": -34.892933,
      "longitude": 138.553001,
      "street": "A7 - Port Rd",
      "city": "Allenby Gardens",
      "type": "mobile",
      "timestamp": "2026-01-25T00:00:15Z",
      "reported_at": "2026-01-24T17:51:01Z"
    }
  ]
}
