{
  "radars": [
    {
      "id": "70c2909b-0e5f-4cc1-9ba8-049bb48693bb",
      "latitude": -34.856754,
      "longitude": 138.529123,
      "street": "Addison Rd",
      "city": "Pennington",
      "type": "mobile",
      "timestamp": "2025-12-08T07:43:47Z",
      "reported_at": "2025-12-08T07:13:33Z"
    },
    {
      "id": "d2f166f9-1b00-4e8e-a6bc-7ad4d842faf2",
      "latitude": -34.92011,
      "longitude": 138.657857,
      "street": "The Parade",
      "city": "Kensington Park",
      "type": "mobile",
      "timestamp": "2025-12-08T07:43:47Z",
      "reported_at": "2025-12-08T05:02:00Z"
    },
    {
      "id": "f568cab3-031c-4dc8-b588-3c7f1ee7e6d2",
      "latitude": -34.917806,
      "longitude": 138.631756,
      "street": "Osmond Tce",
      "city": "Norwood",
      "type": "mobile",
      "timestamp": "2025-12-08T07:43:47Z",
      "reported_at": "2025-12-08T06:31:34Z"
    },
    {
      "id": "932f2a30-d7ce-4b68-858d-e171a7199377",
      "latitude": -34.916375,
      "longitude": 138.676309,
      "street": "Penfold Rd",
      "city": "Magill",
      "type": "mobile",
      "timestamp": "2025-12-08T07:43:47Z",
      "reported_at": "2025-12-08T06:59:49Z"
    },
    {
      "id": "73ddf047-ec60-41bd-a342-87135096d26f",
      "latitude": -34.80281,
      "longitude": 138.611385,
      "street": "Elder Smith Rd",
      "city": "Mawson Lakes",
      "type": "mobile",
      "timestamp": "2025-12-08T07:43:47Z",
      "reported_at": "2025-12-08T07:22:26Z"
    },
    {
      "id": "f82c47a3-fb81-4875-8ec7-3ec75ba7018c",
      "latitude": -34.900881,
      "longitude": 138.605451,
      "street": "R1 - Robe Tce (City Ring Route)",
      "city": "North Adelaide",
      "type": "mobile",
      "timestamp": "2025-12-08T07:43:47Z",
      "reported_at": "2025-12-08T06:22:10Z"
    },
    {
      "id": "b7f06441-8975-4aba-84b6-dd5a8fe6eda9",
      "latitude": -34.850428,
      "longitude": 138.55076,
      "street": "A16 - Grand Junction Rd",
      "city": "Wingfield",
      "type": "mobile",
      "timestamp": "2025-12-08T07:43:47Z",
      "reported_at": "2025-12-08T07:24:34Z"
    }
  ]
}
