{
  "radars": [
    {
      "id": "efe7aefa-acd2-45cc-babe-c28e1d7bef91",
      "latitude": -34.907331,
      "longitude": 138.653863,
      "street": "Gwynne St",
      "city": "Firle",
      "type": "mobile",
      "timestamp": "2025-12-09T23:20:13Z",
      "reported_at": "2025-12-09T21:13:39Z"
    },
    {
      "id": "f53fa59f-c3b6-4974-81ff-9c3a48569980",
      "latitude": -34.900104,
      "longitude": 138.690755,
      "street": "Morialta Rd",
      "city": "Rostrevor",
      "type": "mobile",
      "timestamp": "2025-12-09T23:20:13Z",
      "reported_at": "2025-12-09T20:56:53Z"
    },
    {
      "id": "bd42395a-2263-458b-b1ea-90f633d41363",
      "latitude": -34.881212,
      "longitude": 138.681467,
      "street": "Graves St",
      "city": "Newton",
      "type": "mobile",
      "timestamp": "2025-12-09T23:20:13Z",
      "reported_at": "2025-12-09T21:12:35Z"
    },
    {
      "id": "d076ada4-6014-4b06-9de2-c4802b685895",
      "latitude": -34.861472,
      "longitude": 138.679837,
      "street": "Balmoral Rd",
      "city": "Dernancourt",
      "type": "mobile",
      "timestamp": "2025-12-09T23:20:13Z",
      "reported_at": "2025-12-09T22:37:54Z"
    },
    {
      "id": "59f08738-f943-4811-80f5-579a1323a3e3",
      "latitude": -34.848395,
      "longitude": 138.516693,
      "street": "Gray Tce",
      "city": "Rosewater",
      "type": "mobile",
      "timestamp": "2025-12-09T23:20:13Z",
      "reported_at": "2025-12-09T22:52:49Z"
    },
    {
      "id": "f84c04ca-7fa3-4f22-b674-2fa43e8e6d39",
      "latitude": -34.884523,
      "longitude": 138.700807,
      "street": "Maryvale Rd",
      "city": "Athelstone",
      "type": "mobile",
      "timestamp": "2025-12-09T23:20:13Z",
      "reported_at": "2025-12-09T22:27:44Z"
    },
    {
      "id": "423e4983-525f-472a-a1b7-400e5941759c",
      "latitude": -34.990476,
      "longitude": 138.599085,
      "street": "Springbank Rd",
      "city": "Colonel Light Gardens",
      "type": "mobile",
      "timestamp": "2025-12-09T23:20:13Z",
      "reported_at": "2025-12-09T22:49:39Z"
    },
    {
      "id": "76df4979-bc00-4961-a373-c21732858276",
      "latitude": -34.852463,
      "longitude": 138.509224,
      "street": "A7 - Port Rd",
      "city": "Queenstown",
      "type": "mobile",
      "timestamp": "2025-12-09T23:20:13Z",
      "reported_at": "2025-12-09T22:48:14Z"
    },
    {
      "id": "f5ce619e-f16c-4c8b-831f-2d90a8f0e73e",
      "latitude": -34.924409,
      "longitude": 138.6184,
      "street": "R1 - Dequetteville Tce (City Ring Route)",
      "city": "Adelaide",
      "type": "mobile",
      "timestamp": "2025-12-09T23:20:13Z",
      "reported_at": "2025-12-09T22:16:30Z"
    },
    {
      "id": "10d37dbc-5d6d-46d2-a7b3-cfaa761d7072",
      "latitude": -34.974961,
      "longitude": 138.573482,
      "street": "A2 - South Rd",
      "city": "Edwardstown",
      "type": "mobile",
      "timestamp": "2025-12-09T23:20:13Z",
      "reported_at": "2025-12-09T22:34:15Z"
    },
    {
      "id": "b93d9d91-0c32-4ac2-b2e2-346b0b381918",
      "latitude": -34.86095,
      "longitude": 138.683894,
      "street": "A11 - Lower North East Rd",
      "city": "Dernancourt",
      "type": "mobile",
      "timestamp": "2025-12-09T23:20:13Z",
      "reported_at": "2025-12-09T21:03:49Z"
    },
    {
      "id": "4f0230a2-1199-4ba2-8175-94627e860d3c",
      "latitude": -34.839713,
      "longitude": 138.593316,
      "street": "A22 - Cavan Rd",
      "city": "Dry Creek",
      "type": "mobile",
      "timestamp": "2025-12-09T23:20:13Z",
      "reported_at": "2025-12-09T22:17:49Z"
    },
    {
      "id": "206d27f6-a423-4992-90aa-b4fa2fbb8780",
      "latitude": -34.802717,
      "longitude": 138.637065,
      "street": "A20 - Main North Rd",
      "city": "Parafield",
      "type": "mobile",
      "timestamp": "2025-12-09T23:20:13Z",
      "reported_at": "2025-12-09T23:14:55Z"
    }
  ]
}
