{
  "radars": [
    {
      "id": "d3b8cb52-37f9-48c9-8808-76d87bae7c8e",
      "latitude": -35.027924,
      "longitude": 138.532835,
      "street": "Neath Av",
      "city": "South Brighton",
      "type": "mobile",
      "timestamp": "2025-12-06T06:51:21Z",
      "reported_at": "2025-12-06T05:56:19Z"
    },
    {
      "id": "800a2616-5ef8-4b90-aa3a-1d44fb6adef6",
      "latitude": -34.973897,
      "longitude": 138.573368,
      "street": "De Laine Av",
      "city": "Edwardstown",
      "type": "mobile",
      "timestamp": "2025-12-06T06:51:21Z",
      "reported_at": "2025-12-06T05:04:52Z"
    },
    {
      "id": "d2f9a5c3-2d68-4b89-ae7b-9a3e31cfedb5",
      "latitude": -35.023218,
      "longitude": 138.525845,
      "street": "Lewis St",
      "city": "Brighton",
      "type": "mobile",
      "timestamp": "2025-12-06T06:51:21Z",
      "reported_at": "2025-12-06T06:01:43Z"
    },
    {
      "id": "632ca5e4-2159-492c-944b-ff0227061980",
      "latitude": -35.008026,
      "longitude": 138.5619,
      "street": "Alawoona Av",
      "city": "Mitchell Park",
      "type": "mobile",
      "timestamp": "2025-12-06T06:51:21Z",
      "reported_at": "2025-12-06T05:02:27Z"
    },
    {
      "id": "c288ac8e-c203-4244-8adf-30825f200ae8",
      "latitude": -34.94942,
      "longitude": 138.567882,
      "street": "Tennyson St",
      "city": "Kurralta Park",
      "type": "mobile",
      "timestamp": "2025-12-06T06:51:21Z",
      "reported_at": "2025-12-06T05:37:02Z"
    },
    {
      "id": "737d215e-96ff-445f-95ca-d82eabb00d9d",
      "latitude": -34.968347,
      "longitude": 138.543643,
      "street": "Stonehouse Av",
      "city": "Camden Park",
      "type": "mobile",
      "timestamp": "2025-12-06T06:51:21Z",
      "reported_at": "2025-12-06T05:13:38Z"
    },
    {
      "id": "eb8e8a68-0a19-4606-a530-dcad4c38351a",
      "latitude": -34.72133,
      "longitude": 138.683527,
      "street": "Unknown Street",
      "city": "Elizabeth East",
      "type": "mobile",
      "timestamp": "2025-12-06T06:51:21Z",
      "reported_at": "2025-12-06T05:09:58Z"
    },
    {
      "id": "eabd7672-b763-44ae-b667-8cf4c0452061",
      "latitude": -35.125508,
      "longitude": 138.646447,
      "street": "Kangarilla Rd",
      "city": "Clarendon",
      "type": "mobile",
      "timestamp": "2025-12-06T06:51:21Z",
      "reported_at": "2025-12-06T05:17:57Z"
    },
    {
      "id": "67f9b958-210b-4805-bb80-0c8fe7b4b43c",
      "latitude": -34.99333,
      "longitude": 138.528023,
      "street": "Diagonal Rd",
      "city": "Somerton Park",
      "type": "mobile",
      "timestamp": "2025-12-06T06:51:21Z",
      "reported_at": "2025-12-06T06:34:59Z"
    },
    {
      "id": "c9f1251b-1f30-4e44-813e-4e389d247315",
      "latitude": -34.992283,
      "longitude": 138.585135,
      "street": "Daws Rd",
      "city": "Daw Park",
      "type": "mobile",
      "timestamp": "2025-12-06T06:51:21Z",
      "reported_at": "2025-12-06T05:01:23Z"
    },
    {
      "id": "0469bbbe-eeac-4925-920d-a14737140041",
      "latitude": -34.99044,
      "longitude": 138.599893,
      "street": "Springbank Rd",
      "city": "Colonel Light Gardens",
      "type": "mobile",
      "timestamp": "2025-12-06T06:51:21Z",
      "reported_at": "2025-12-06T05:13:14Z"
    },
    {
      "id": "dd439f74-eb1c-4d9c-8810-e94b946be852",
      "latitude": -34.955996,
      "longitude": 138.567034,
      "street": "A5 - Anzac Hwy",
      "city": "Kurralta Park",
      "type": "mobile",
      "timestamp": "2025-12-06T06:51:21Z",
      "reported_at": "2025-12-06T04:59:16Z"
    },
    {
      "id": "7295127b-b2e4-4843-92cd-54a87bd147e9",
      "latitude": -35.029238,
      "longitude": 138.523937,
      "street": "A15 - Brighton Rd",
      "city": "Seacliff",
      "type": "mobile",
      "timestamp": "2025-12-06T06:51:21Z",
      "reported_at": "2025-12-06T06:41:28Z"
    },
    {
      "id": "a0e0991d-4f6c-41bd-a396-a6985711f4c3",
      "latitude": -34.972853,
      "longitude": 138.573426,
      "street": "A2 - South Rd",
      "city": "Clarence Gardens",
      "type": "mobile",
      "timestamp": "2025-12-06T06:51:21Z",
      "reported_at": "2025-12-06T05:05:53Z"
    },
    {
      "id": "8ff96e6b-ec89-4293-a23b-5c5344f4e3e6",
      "latitude": -34.800039,
      "longitude": 138.717065,
      "street": "A11 - Hancock Rd",
      "city": "Surrey Downs",
      "type": "mobile",
      "timestamp": "2025-12-06T06:51:21Z",
      "reported_at": "2025-12-06T06:19:33Z"
    }
  ]
}
