{
  "radars": [
    {
      "id": "abde08b3-ade6-414a-b0d5-cd57e072387e",
      "latitude": -34.951387,
      "longitude": 138.550989,
      "street": "Harvey Av",
      "city": "Netley",
      "type": "mobile",
      "timestamp": "2026-01-19T03:00:19Z",
      "reported_at": "2026-01-19T00:38:32Z"
    },
    {
      "id": "3edce6e8-6672-437e-bded-6000ca530a87",
      "latitude": -34.98549,
      "longitude": 138.566016,
      "street": "Adelaide Tce",
      "city": "Edwardstown",
      "type": "mobile",
      "timestamp": "2026-01-19T03:00:19Z",
      "reported_at": "2026-01-19T02:03:42Z"
    },
    {
      "id": "098af35a-4bbd-4ba8-82a7-b6695695f4ae",
      "latitude": -34.95994,
      "longitude": 138.550119,
      "street": "Mooringe Av",
      "city": "North Plympton",
      "type": "mobile",
      "timestamp": "2026-01-19T03:00:19Z",
      "reported_at": "2026-01-18T22:24:33Z"
    },
    {
      "id": "ad847c0c-cda4-472a-a52b-cc2a3b637089",
      "latitude": -34.963747,
      "longitude": 138.563622,
      "street": "Winifred Av",
      "city": "South Plympton",
      "type": "mobile",
      "timestamp": "2026-01-19T03:00:19Z",
      "reported_at": "2026-01-18T21:05:47Z"
    },
    {
      "id": "164e8e89-79cb-4ecb-81f1-25402b33960f",
      "latitude": -34.865483,
      "longitude": 138.661656,
      "street": "Sudholz Rd",
      "city": "Paradise",
      "type": "mobile",
      "timestamp": "2026-01-19T03:00:19Z",
      "reported_at": "2026-01-19T02:41:05Z"
    },
    {
      "id": "05f0e674-086f-4b4f-8dc3-64dfeafc6129",
      "latitude": -34.99047,
      "longitude": 138.599207,
      "street": "Springbank Rd",
      "city": "Colonel Light Gardens",
      "type": "mobile",
      "timestamp": "2026-01-19T03:00:19Z",
      "reported_at": "2026-01-18T22:50:34Z"
    },
    {
      "id": "fe79eadf-0742-4834-89aa-aab50d4ba197",
      "latitude": -34.979899,
      "longitude": 138.567297,
      "street": "Raglan Av",
      "city": "Edwardstown",
      "type": "mobile",
      "timestamp": "2026-01-19T03:00:19Z",
      "reported_at": "2026-01-18T21:45:27Z"
    },
    {
      "id": "65bbd521-6bd7-45f8-a8c2-b6c17fa5851b",
      "latitude": -35.010842,
      "longitude": 138.583583,
      "street": "Ayliffes Rd",
      "city": "St. Marys",
      "type": "mobile",
      "timestamp": "2026-01-19T03:00:19Z",
      "reported_at": "2026-01-19T01:02:17Z"
    },
    {
      "id": "ee4d9558-06e6-4784-94cd-328eb4f91340",
      "latitude": -34.863316,
      "longitude": 138.661517,
      "street": "Sudholz Rd",
      "city": "Windsor Gardens",
      "type": "mobile",
      "timestamp": "2026-01-19T03:00:19Z",
      "reported_at": "2026-01-19T02:40:08Z"
    },
    {
      "id": "1246724a-e97a-43a5-8a97-23bf36dbd751",
      "latitude": -35.021451,
      "longitude": 138.55919,
      "street": "A14 - Marion Rd",
      "city": "Sturt",
      "type": "mobile",
      "timestamp": "2026-01-19T03:00:19Z",
      "reported_at": "2026-01-19T02:33:00Z"
    },
    {
      "id": "9eda3a3a-dbc6-4855-8c4d-00e352520528",
      "latitude": -34.926265,
      "longitude": 138.5176,
      "street": "A15 - Tapleys Hill Rd",
      "city": "Fulham",
      "type": "mobile",
      "timestamp": "2026-01-19T03:00:19Z",
      "reported_at": "2026-01-19T02:53:03Z"
    },
    {
      "id": "7ff99e18-0d4c-4665-9f47-20e7a75b21ac",
      "latitude": -34.816359,
      "longitude": 138.676584,
      "street": "A18 - McIntyre Rd",
      "city": "Modbury",
      "type": "mobile",
      "timestamp": "2026-01-19T03:00:19Z",
      "reported_at": "2026-01-19T02:51:25Z"
    },
    {
      "id": "ca4526b9-8fb4-4927-bb0a-db689b572d90",
      "latitude": -34.87391,
      "longitude": 138.697353,
      "street": "B31 - Gorge Rd",
      "city": "Athelstone",
      "type": "mobile",
      "timestamp": "2026-01-19T03:00:19Z",
      "reported_at": "2026-01-19T02:50:13Z"
    },
    {
      "id": "4c26884c-a0a2-461e-b859-8322f4a16567",
      "latitude": -34.823299,
      "longitude": 138.710625,
      "street": "A10 - North East Rd",
      "city": "Ridgehaven",
      "type": "mobile",
      "timestamp": "2026-01-19T03:00:19Z",
      "reported_at": "2026-01-19T02:27:43Z"
    }
  ]
}
