{
  "radars": [
    {
      "id": "12981322-f4f1-45f2-a198-6bbbec877991",
      "latitude": -34.954839,
      "longitude": 138.558256,
      "street": "Birdwood Tce",
      "city": "North Plympton",
      "type": "mobile",
      "timestamp": "2025-12-10T09:25:47Z",
      "reported_at": "2025-12-10T07:18:28Z"
    },
    {
      "id": "020fc71a-9c5e-455d-8e81-cd1156d68de1",
      "latitude": -34.981552,
      "longitude": 138.588576,
      "street": "Richmond Av",
      "city": "Colonel Light Gardens",
      "type": "mobile",
      "timestamp": "2025-12-10T09:25:47Z",
      "reported_at": "2025-12-10T05:10:00Z"
    },
    {
      "id": "72e811b4-e19e-4bba-9c11-2c69c61d7102",
      "latitude": -34.949623,
      "longitude": 138.564487,
      "street": "Daly St",
      "city": "Kurralta Park",
      "type": "mobile",
      "timestamp": "2025-12-10T09:25:47Z",
      "reported_at": "2025-12-10T05:46:15Z"
    },
    {
      "id": "f07ff66d-247e-43e2-a83a-de166ccdff60",
      "latitude": -34.97197,
      "longitude": 138.552448,
      "street": "South Tce",
      "city": "Plympton Park",
      "type": "mobile",
      "timestamp": "2025-12-10T09:25:47Z",
      "reported_at": "2025-12-10T06:38:42Z"
    },
    {
      "id": "e33d7dce-08d3-4ac8-8041-43528e6a5e45",
      "latitude": -34.961901,
      "longitude": 138.563485,
      "street": "Beckman St",
      "city": "Plympton",
      "type": "mobile",
      "timestamp": "2025-12-10T09:25:47Z",
      "reported_at": "2025-12-10T06:17:49Z"
    },
    {
      "id": "1c2b4dca-cf27-4e52-a753-14367bf5af27",
      "latitude": -34.963262,
      "longitude": 138.581492,
      "street": "East Av",
      "city": "Clarence Park",
      "type": "mobile",
      "timestamp": "2025-12-10T09:25:47Z",
      "reported_at": "2025-12-10T05:26:28Z"
    },
    {
      "id": "2260bb27-c4dc-4133-8502-0a9ecadff3eb",
      "latitude": -34.949453,
      "longitude": 138.5672,
      "street": "Tennyson St",
      "city": "Kurralta Park",
      "type": "mobile",
      "timestamp": "2025-12-10T09:25:47Z",
      "reported_at": "2025-12-10T06:00:58Z"
    },
    {
      "id": "24023bff-0ea2-4885-8f22-1e489bbf147d",
      "latitude": -34.990485,
      "longitude": 138.598913,
      "street": "Springbank Rd",
      "city": "Colonel Light Gardens",
      "type": "mobile",
      "timestamp": "2025-12-10T09:25:47Z",
      "reported_at": "2025-12-10T07:29:42Z"
    },
    {
      "id": "4631672b-cbff-4377-bd20-138526c947ee",
      "latitude": -34.980341,
      "longitude": 138.561722,
      "street": "Raglan Av",
      "city": "South Plympton",
      "type": "mobile",
      "timestamp": "2025-12-10T09:25:47Z",
      "reported_at": "2025-12-10T08:44:46Z"
    },
    {
      "id": "42009b3f-82e9-409d-8f23-0570c93a5fd3",
      "latitude": -34.869591,
      "longitude": 138.481323,
      "street": "Military Rd",
      "city": "West Lakes Shore",
      "type": "mobile",
      "timestamp": "2025-12-10T09:25:47Z",
      "reported_at": "2025-12-10T08:38:44Z"
    },
    {
      "id": "a8d7e21c-cf81-4610-9cff-2c0348ff7666",
      "latitude": -34.861094,
      "longitude": 138.618404,
      "street": "A17 - Hampstead Rd",
      "city": "Lightsview",
      "type": "mobile",
      "timestamp": "2025-12-10T09:25:47Z",
      "reported_at": "2025-12-10T09:19:29Z"
    },
    {
      "id": "29434218-632a-4fb3-8caf-a35472185116",
      "latitude": -34.881733,
      "longitude": 138.62337,
      "street": "A10 - North East Rd",
      "city": "Manningham",
      "type": "mobile",
      "timestamp": "2025-12-10T09:25:47Z",
      "reported_at": "2025-12-10T09:05:47Z"
    },
    {
      "id": "fc91bffd-4cf7-43fc-b879-3c68e4122c10",
      "latitude": -34.967004,
      "longitude": 138.55027,
      "street": "A5 - Anzac Hwy",
      "city": "Plympton",
      "type": "mobile",
      "timestamp": "2025-12-10T09:25:47Z",
      "reported_at": "2025-12-10T08:35:38Z"
    }
  ]
}
