{
  "radars": [
    {
      "id": "568d5917-f939-4561-aa7c-fdfd1e54b2de",
      "latitude": -34.85731,
      "longitude": 138.505029,
      "street": "Webb St",
      "city": "Port Adelaide",
      "type": "mobile",
      "timestamp": "2025-11-21T09:42:43Z",
      "reported_at": "2025-11-21T06:18:59Z"
    },
    {
      "id": "36956d1e-09cd-4da2-b79a-6974f48bc7eb",
      "latitude": -34.867952,
      "longitude": 138.565762,
      "street": "Days Rd",
      "city": "Ferryden Park",
      "type": "mobile",
      "timestamp": "2025-11-21T09:42:43Z",
      "reported_at": "2025-11-21T05:23:24Z"
    },
    {
      "id": "9bb5d43d-9a25-43a6-9e9e-8842a45361a3",
      "latitude": -34.861801,
      "longitude": 138.526328,
      "street": "Torrens Rd",
      "city": "Pennington",
      "type": "mobile",
      "timestamp": "2025-11-21T09:42:43Z",
      "reported_at": "2025-11-21T07:09:30Z"
    },
    {
      "id": "e30ca1c7-be61-4aff-a72c-6e309f461b6f",
      "latitude": -34.718408,
      "longitude": 138.761687,
      "street": "Black Top Rd",
      "city": "One Tree Hill",
      "type": "mobile",
      "timestamp": "2025-11-21T09:42:43Z",
      "reported_at": "2025-11-21T05:52:40Z"
    },
    {
      "id": "5dc53a08-9b28-4f8f-843e-db8f2c3783c4",
      "latitude": -34.806645,
      "longitude": 138.69559,
      "street": "Grenfell Rd",
      "city": "Wynn Vale",
      "type": "mobile",
      "timestamp": "2025-11-21T09:42:43Z",
      "reported_at": "2025-11-21T09:23:14Z"
    },
    {
      "id": "d126932e-afba-48b0-854b-1bc97e807219",
      "latitude": -34.862586,
      "longitude": 138.508374,
      "street": "Old Port Rd",
      "city": "Queenstown",
      "type": "mobile",
      "timestamp": "2025-11-21T09:42:43Z",
      "reported_at": "2025-11-21T09:09:52Z"
    },
    {
      "id": "631ffcdb-dec3-4385-b5fe-e4df47ca363f",
      "latitude": -34.861267,
      "longitude": 138.601053,
      "street": "A1 - Main North Rd",
      "city": "Blair Athol",
      "type": "mobile",
      "timestamp": "2025-11-21T09:42:43Z",
      "reported_at": "2025-11-21T09:14:58Z"
    },
    {
      "id": "f6b85762-981f-483f-b2c9-3657add2dd29",
      "latitude": -34.75965,
      "longitude": 138.675079,
      "street": "A20 - Main North Rd",
      "city": "Salisbury Park",
      "type": "mobile",
      "timestamp": "2025-11-21T09:42:43Z",
      "reported_at": "2025-11-21T09:32:49Z"
    }
  ]
}
