{
  "radars": [
    {
      "id": "5e6e2bf3-14f2-4c8f-b9f6-ada39ce05749",
      "latitude": -34.892955,
      "longitude": 138.660128,
      "street": "Hectorville Rd",
      "city": "Hectorville",
      "type": "mobile",
      "timestamp": "2025-11-18T08:51:46Z",
      "reported_at": "2025-11-18T05:37:06Z"
    },
    {
      "id": "4ea0a06d-f636-4507-9337-b1816f88603b",
      "latitude": -34.915443,
      "longitude": 138.587128,
      "street": "War Memorial Dr",
      "city": "North Adelaide",
      "type": "mobile",
      "timestamp": "2025-11-18T08:51:46Z",
      "reported_at": "2025-11-18T06:55:43Z"
    },
    {
      "id": "9fea2a40-496f-4277-bcb7-515ccd465de3",
      "latitude": -34.992433,
      "longitude": 138.584512,
      "street": "Daws Rd",
      "city": "Daw Park",
      "type": "mobile",
      "timestamp": "2025-11-18T08:51:46Z",
      "reported_at": "2025-11-18T07:52:32Z"
    },
    {
      "id": "e27c5df6-b9d3-4f4a-8971-4afb95a52b0d",
      "latitude": -34.851474,
      "longitude": 138.509443,
      "street": "A7 - Commercial Rd",
      "city": "Port Adelaide",
      "type": "mobile",
      "timestamp": "2025-11-18T08:51:46Z",
      "reported_at": "2025-11-18T08:34:37Z"
    },
    {
      "id": "745676cb-fa31-46aa-9679-9145b7a923c3",
      "latitude": -34.858976,
      "longitude": 138.512123,
      "street": "A7 - Port Rd",
      "city": "Queenstown",
      "type": "mobile",
      "timestamp": "2025-11-18T08:51:46Z",
      "reported_at": "2025-11-18T08:43:58Z"
    },
    {
      "id": "7750cbff-b4c5-4695-9a54-cdd975e7f9d1",
      "latitude": -34.91492,
      "longitude": 138.637848,
      "street": "B27 - Magill Rd",
      "city": "Maylands",
      "type": "mobile",
      "timestamp": "2025-11-18T08:51:46Z",
      "reported_at": "2025-11-18T08:25:40Z"
    },
    {
      "id": "1b867d8b-4477-4aae-b71d-9e62af395b6b",
      "latitude": -34.917246,
      "longitude": 138.619629,
      "street": "A11 - North Tce",
      "city": "Kent Town",
      "type": "mobile",
      "timestamp": "2025-11-18T08:51:46Z",
      "reported_at": "2025-11-18T08:30:08Z"
    },
    {
      "id": "f1fee08c-a1ac-473d-bced-235f9dad09dd",
      "latitude": -34.876245,
      "longitude": 138.694495,
      "street": "B31 - Gorge Rd",
      "city": "Athelstone",
      "type": "mobile",
      "timestamp": "2025-11-18T08:51:46Z",
      "reported_at": "2025-11-18T05:35:29Z"
    },
    {
      "id": "302f2148-dc45-432b-8b77-b4fb27de1127",
      "latitude": -34.827529,
      "longitude": 138.696941,
      "street": "A10 - North East Rd",
      "city": "St. Agnes",
      "type": "mobile",
      "timestamp": "2025-11-18T08:51:46Z",
      "reported_at": "2025-11-18T05:27:30Z"
    },
    {
      "id": "0e0e05a6-bc13-4d26-bad5-42dad3262e9d",
      "latitude": -34.999187,
      "longitude": 138.710831,
      "street": "M1 - South Eastern Fwy",
      "city": "Crafers",
      "type": "mobile",
      "timestamp": "2025-11-18T08:51:46Z",
      "reported_at": "2025-11-18T08:34:25Z"
    },
    {
      "id": "8f6af741-0f5a-4ff2-94ca-3598d9ce2914",
      "latitude": -34.869565,
      "longitude": 138.570633,
      "street": "M2 - North-South Mwy",
      "city": "Croydon Park",
      "type": "mobile",
      "timestamp": "2025-11-18T08:51:46Z",
      "reported_at": "2025-11-18T08:36:59Z"
    }
  ]
}
