{
  "radars": [
    {
      "id": "32449f6e-4d87-4215-8764-62e3f852839b",
      "latitude": -34.693824,
      "longitude": 138.683412,
      "street": "Konanda Rd",
      "city": "Smithfield",
      "type": "mobile",
      "timestamp": "2026-01-10T09:00:15Z",
      "reported_at": "2026-01-10T05:08:25Z"
    },
    {
      "id": "ee51a955-d188-4b32-81ac-8964f3eece62",
      "latitude": -34.945237,
      "longitude": 138.506198,
      "street": "West Beach Rd",
      "city": "West Beach",
      "type": "mobile",
      "timestamp": "2026-01-10T09:00:15Z",
      "reported_at": "2026-01-10T07:50:27Z"
    },
    {
      "id": "34e2deee-0a1d-4e32-8343-fd7b1a512889",
      "latitude": -34.681344,
      "longitude": 138.680358,
      "street": "Coventry Rd",
      "city": "Smithfield Plains",
      "type": "mobile",
      "timestamp": "2026-01-10T09:00:15Z",
      "reported_at": "2026-01-10T05:41:28Z"
    },
    {
      "id": "3da9d439-62d8-4b6d-a183-d3bfed59cf1b",
      "latitude": -34.668073,
      "longitude": 138.56085,
      "street": "Unknown Street",
      "city": "Virginia",
      "type": "mobile",
      "timestamp": "2026-01-10T09:00:15Z",
      "reported_at": "2026-01-10T05:00:31Z"
    },
    {
      "id": "082370ab-3277-48f0-9701-1eeffd887f27",
      "latitude": -35.022959,
      "longitude": 138.585011,
      "street": "Shepherds Hill Rd",
      "city": "Eden Hills",
      "type": "mobile",
      "timestamp": "2026-01-10T09:00:15Z",
      "reported_at": "2026-01-10T08:48:09Z"
    },
    {
      "id": "5b3ada77-c55e-4f4f-b074-a63601bd2c6c",
      "latitude": -34.673337,
      "longitude": 138.678246,
      "street": "Peachey Rd",
      "city": "Smithfield Plains",
      "type": "mobile",
      "timestamp": "2026-01-10T09:00:15Z",
      "reported_at": "2026-01-10T05:23:05Z"
    },
    {
      "id": "9a796d90-1a2b-43be-bc9a-bb7641ccfe3b",
      "latitude": -34.678478,
      "longitude": 138.696733,
      "street": "A20 - Main North Rd",
      "city": "Evanston South",
      "type": "mobile",
      "timestamp": "2026-01-10T09:00:15Z",
      "reported_at": "2026-01-10T07:52:11Z"
    },
    {
      "id": "e90e8812-37cc-49b6-ae48-935f64c61676",
      "latitude": -34.761135,
      "longitude": 138.588517,
      "street": "M2 - North-South Mwy",
      "city": "Bolivar",
      "type": "mobile",
      "timestamp": "2026-01-10T09:00:15Z",
      "reported_at": "2026-01-10T06:36:43Z"
    },
    {
      "id": "89490cf5-0478-4373-8e6a-de7b484221ee",
      "latitude": -34.826244,
      "longitude": 138.586108,
      "street": "A9 - Salisbury Hwy",
      "city": "Dry Creek",
      "type": "mobile",
      "timestamp": "2026-01-10T09:00:15Z",
      "reported_at": "2026-01-10T08:17:45Z"
    }
  ]
}
