{
  "radars": [
    {
      "id": "5f4ec8a5-ac33-434a-92c2-eb7f4565dd5b",
      "latitude": -35.015578,
      "longitude": 138.540743,
      "street": "Morphett Rd",
      "city": "Oaklands Park",
      "type": "mobile",
      "timestamp": "2025-12-06T10:41:55Z",
      "reported_at": "2025-12-06T09:38:44Z"
    },
    {
      "id": "3b68c162-90a3-404e-b93e-101711a818af",
      "latitude": -35.018256,
      "longitude": 138.53983,
      "street": "Sturt Rd",
      "city": "Warradale",
      "type": "mobile",
      "timestamp": "2025-12-06T10:41:55Z",
      "reported_at": "2025-12-06T09:38:14Z"
    },
    {
      "id": "aa168596-1d88-4f99-81eb-4ce00e58c54e",
      "latitude": -34.992536,
      "longitude": 138.582422,
      "street": "Daws Rd",
      "city": "Melrose Park",
      "type": "mobile",
      "timestamp": "2025-12-06T10:41:55Z",
      "reported_at": "2025-12-06T09:08:57Z"
    },
    {
      "id": "209fb573-060f-4b98-9fce-5dfe391dbe99",
      "latitude": -34.973942,
      "longitude": 138.57339,
      "street": "A2 - South Rd",
      "city": "Edwardstown",
      "type": "mobile",
      "timestamp": "2025-12-06T10:41:55Z",
      "reported_at": "2025-12-06T08:13:29Z"
    },
    {
      "id": "ac09ddf1-e6c3-4549-8791-de094380e6f4",
      "latitude": -34.975316,
      "longitude": 138.573604,
      "street": "A2 - South Rd",
      "city": "Clarence Gardens",
      "type": "mobile",
      "timestamp": "2025-12-06T10:41:55Z",
      "reported_at": "2025-12-06T09:02:59Z"
    },
    {
      "id": "634a0636-cbb9-472e-aee5-e2a544435f17",
      "latitude": -34.851004,
      "longitude": 138.712321,
      "street": "A11 - Lower North East Rd",
      "city": "Highbury",
      "type": "mobile",
      "timestamp": "2025-12-06T10:41:55Z",
      "reported_at": "2025-12-06T09:11:54Z"
    },
    {
      "id": "6652f0d5-ae6f-4c71-a2db-45bcb01ef123",
      "latitude": -34.95508,
      "longitude": 138.568448,
      "street": "A5 - Anzac Hwy",
      "city": "Kurralta Park",
      "type": "mobile",
      "timestamp": "2025-12-06T10:41:55Z",
      "reported_at": "2025-12-06T06:37:33Z"
    },
    {
      "id": "89788678-267a-4ae7-bcfb-5c9967ca6e44",
      "latitude": -35.035865,
      "longitude": 138.624626,
      "street": "B29 - Main Rd",
      "city": "Coromandel Valley",
      "type": "mobile",
      "timestamp": "2025-12-06T10:41:55Z",
      "reported_at": "2025-12-06T08:16:59Z"
    }
  ]
}
