{
  "radars": [
    {
      "id": "8e7ceabb-caa6-48ad-90d2-58d1a05130ad",
      "latitude": -34.912281,
      "longitude": 138.535012,
      "street": "Hartley Rd",
      "city": "Flinders Park",
      "type": "mobile",
      "timestamp": "2026-01-24T06:30:14Z",
      "reported_at": "2026-01-24T05:29:05Z"
    },
    {
      "id": "75032ef2-d521-4e62-a453-068d3f142cfd",
      "latitude": -35.025288,
      "longitude": 138.61881,
      "street": "Coromandel Pde",
      "city": "Blackwood",
      "type": "mobile",
      "timestamp": "2026-01-24T06:30:14Z",
      "reported_at": "2026-01-24T03:00:07Z"
    },
    {
      "id": "f7a26712-1c31-4092-89da-82a5af8e2466",
      "latitude": -34.912894,
      "longitude": 138.509669,
      "street": "Marlborough St",
      "city": "Fulham Gardens",
      "type": "mobile",
      "timestamp": "2026-01-24T06:30:14Z",
      "reported_at": "2026-01-24T03:46:28Z"
    },
    {
      "id": "97825139-be85-4b5e-af4a-5c9a3fea97ca",
      "latitude": -34.956139,
      "longitude": 138.508851,
      "street": "Military Rd",
      "city": "West Beach",
      "type": "mobile",
      "timestamp": "2026-01-24T06:30:14Z",
      "reported_at": "2026-01-24T04:52:49Z"
    },
    {
      "id": "42dab5b1-cfda-4ed4-8251-96f5f2543d51",
      "latitude": -34.901107,
      "longitude": 138.576481,
      "street": "Chief St",
      "city": "Brompton",
      "type": "mobile",
      "timestamp": "2026-01-24T06:30:14Z",
      "reported_at": "2026-01-24T03:22:29Z"
    },
    {
      "id": "ff151280-d7e3-4aec-a1af-ad82f600c31d",
      "latitude": -34.913639,
      "longitude": 138.575646,
      "street": "Phillips St",
      "city": "Thebarton",
      "type": "mobile",
      "timestamp": "2026-01-24T06:30:14Z",
      "reported_at": "2026-01-24T05:46:35Z"
    },
    {
      "id": "61003377-dcd2-4e74-816d-5b1de8f8e616",
      "latitude": -34.891647,
      "longitude": 138.518089,
      "street": "Trimmer Pde",
      "city": "Seaton",
      "type": "mobile",
      "timestamp": "2026-01-24T06:30:14Z",
      "reported_at": "2026-01-24T05:32:53Z"
    },
    {
      "id": "b99a605c-1f0e-4320-a198-057688e7c0a7",
      "latitude": -34.989471,
      "longitude": 138.724367,
      "street": "Piccadilly Rd",
      "city": "Crafers",
      "type": "mobile",
      "timestamp": "2026-01-24T06:30:14Z",
      "reported_at": "2026-01-24T02:36:59Z"
    },
    {
      "id": "bc788e14-078e-454b-8361-a32787fa2f79",
      "latitude": -34.752373,
      "longitude": 138.634378,
      "street": "Bagster Rd",
      "city": "Salisbury North",
      "type": "mobile",
      "timestamp": "2026-01-24T06:30:14Z",
      "reported_at": "2026-01-24T06:01:52Z"
    },
    {
      "id": "3c881a44-df7f-480c-ac0a-08a3d5199c63",
      "latitude": -34.879949,
      "longitude": 138.503773,
      "street": "Frederick Rd",
      "city": "Seaton",
      "type": "mobile",
      "timestamp": "2026-01-24T06:30:14Z",
      "reported_at": "2026-01-24T06:13:55Z"
    },
    {
      "id": "6e9b801e-2319-462d-aa3b-2c19705a2113",
      "latitude": -34.875606,
      "longitude": 138.561081,
      "street": "Regency Rd",
      "city": "Ferryden Park",
      "type": "mobile",
      "timestamp": "2026-01-24T06:30:14Z",
      "reported_at": "2026-01-24T05:57:30Z"
    },
    {
      "id": "bb42fbdf-01d3-4edc-8bbc-652b2fcd1721",
      "latitude": -34.9048,
      "longitude": 138.491373,
      "street": "Military Rd",
      "city": "Grange",
      "type": "mobile",
      "timestamp": "2026-01-24T06:30:14Z",
      "reported_at": "2026-01-24T05:21:11Z"
    },
    {
      "id": "256fa7d9-1ded-4b04-91ba-b7d41712e8fc",
      "latitude": -34.882372,
      "longitude": 138.503935,
      "street": "Frederick Rd",
      "city": "Grange",
      "type": "mobile",
      "timestamp": "2026-01-24T06:30:14Z",
      "reported_at": "2026-01-24T06:09:54Z"
    },
    {
      "id": "342feb1d-8d64-493d-830b-f8b8519e87cd",
      "latitude": -35.016603,
      "longitude": 138.740813,
      "street": "B33 - Strathalbyn Rd",
      "city": "Aldgate",
      "type": "mobile",
      "timestamp": "2026-01-24T06:30:14Z",
      "reported_at": "2026-01-24T02:46:28Z"
    },
    {
      "id": "f7399e28-e5bc-48b5-9788-e66871c0042c",
      "latitude": -34.804239,
      "longitude": 138.574253,
      "street": "M2 - North-South Mwy",
      "city": "Bolivar",
      "type": "mobile",
      "timestamp": "2026-01-24T06:30:14Z",
      "reported_at": "2026-01-24T06:02:31Z"
    }
  ]
}
