{
  "radars": [
    {
      "id": "83d930f6-51ab-43ba-a6b0-5f599ced4490",
      "latitude": -34.885392,
      "longitude": 138.66287,
      "street": "Spencer St",
      "city": "Campbelltown",
      "type": "mobile",
      "timestamp": "2026-01-23T09:30:15Z",
      "reported_at": "2026-01-23T06:35:28Z"
    },
    {
      "id": "03f4b3dc-0462-4df3-9cf2-950a98055921",
      "latitude": -34.928504,
      "longitude": 138.668242,
      "street": "Hallett Rd",
      "city": "Erindale",
      "type": "mobile",
      "timestamp": "2026-01-23T09:30:15Z",
      "reported_at": "2026-01-23T05:23:22Z"
    },
    {
      "id": "e4fd7b8a-6b2f-4f3e-b075-9dd935d0081c",
      "latitude": -34.93198,
      "longitude": 138.631629,
      "street": "Grant Av",
      "city": "Rose Park",
      "type": "mobile",
      "timestamp": "2026-01-23T09:30:15Z",
      "reported_at": "2026-01-23T05:07:26Z"
    },
    {
      "id": "5a72e495-f88d-4fe2-801c-c6a2a7d5de59",
      "latitude": -34.881029,
      "longitude": 138.685282,
      "street": "Graves St",
      "city": "Newton",
      "type": "mobile",
      "timestamp": "2026-01-23T09:30:15Z",
      "reported_at": "2026-01-23T06:09:41Z"
    },
    {
      "id": "c63cd0fc-b826-4031-87d3-7d6be6742516",
      "latitude": -34.899703,
      "longitude": 138.611654,
      "street": "Walkerville Tce",
      "city": "Gilberton",
      "type": "mobile",
      "timestamp": "2026-01-23T09:30:15Z",
      "reported_at": "2026-01-23T05:59:42Z"
    },
    {
      "id": "8b1a5119-c476-4559-8e01-4f7b5e91219c",
      "latitude": -34.890595,
      "longitude": 138.663168,
      "street": "Hectorville Rd",
      "city": "Hectorville",
      "type": "mobile",
      "timestamp": "2026-01-23T09:30:15Z",
      "reported_at": "2026-01-23T07:30:52Z"
    },
    {
      "id": "7954585d-b003-412d-af0d-57343b966523",
      "latitude": -34.925739,
      "longitude": 138.664819,
      "street": "Kensington Rd",
      "city": "Kensington Gardens",
      "type": "mobile",
      "timestamp": "2026-01-23T09:30:15Z",
      "reported_at": "2026-01-23T08:31:46Z"
    },
    {
      "id": "88717670-785d-418f-b625-53ad98ea92eb",
      "latitude": -35.136639,
      "longitude": 138.525918,
      "street": "Doctors Rd",
      "city": "Morphett Vale",
      "type": "mobile",
      "timestamp": "2026-01-23T09:30:15Z",
      "reported_at": "2026-01-23T08:12:47Z"
    },
    {
      "id": "6c8abbdc-6a2d-43c0-a6bf-af8563308e68",
      "latitude": -34.915434,
      "longitude": 138.676239,
      "street": "Penfold Rd",
      "city": "Magill",
      "type": "mobile",
      "timestamp": "2026-01-23T09:30:15Z",
      "reported_at": "2026-01-23T05:37:58Z"
    },
    {
      "id": "c47b845c-b46c-4da8-9420-11e8e5f02e31",
      "latitude": -34.92394,
      "longitude": 138.566243,
      "street": "Henley Beach Rd",
      "city": "Torrensville",
      "type": "mobile",
      "timestamp": "2026-01-23T09:30:15Z",
      "reported_at": "2026-01-23T09:14:32Z"
    },
    {
      "id": "33dd802f-a627-4a85-82e6-f36d40cff78a",
      "latitude": -34.912891,
      "longitude": 138.684885,
      "street": "B27 - Magill Rd",
      "city": "Magill",
      "type": "mobile",
      "timestamp": "2026-01-23T09:30:15Z",
      "reported_at": "2026-01-23T08:22:37Z"
    },
    {
      "id": "c5dda475-89b1-4444-b80b-61008d857399",
      "latitude": -34.787174,
      "longitude": 138.580592,
      "street": "M2 - North-South Mwy",
      "city": "Bolivar",
      "type": "mobile",
      "timestamp": "2026-01-23T09:30:15Z",
      "reported_at": "2026-01-23T09:16:59Z"
    }
  ]
}
